.cvsignore
EXTERNALS.txt
README.txt
buildout.cfg
paster.cfg
setup.py
bootstrap/bootstrap.py
z3c/__init__.py
z3c.repoexternals.egg-info/PKG-INFO
z3c.repoexternals.egg-info/SOURCES.txt
z3c.repoexternals.egg-info/dependency_links.txt
z3c.repoexternals.egg-info/entry_points.txt
z3c.repoexternals.egg-info/namespace_packages.txt
z3c.repoexternals.egg-info/paster_plugins.txt
z3c.repoexternals.egg-info/requires.txt
z3c.repoexternals.egg-info/top_level.txt
z3c.repoexternals.egg-info/zip-safe
z3c/repoexternals/__init__.py
z3c/repoexternals/tag.py
z3c/repoexternals/tests/EXTERNALS.txt
z3c/repoexternals/tests/__init__.py
z3c/repoexternals/tests/functional.txt
z3c/repoexternals/tests/script.txt
z3c/repoexternals/tests/test.py
