Metadata-Version: 1.0
Name: z3c.repoexternals
Version: 0.2
Summary: Generate externals from a repository
Home-page: http://cheeseshop.python.org/pypi/z3c.repoexternals
Author: Ross Patterson
Author-email: me@rpatteron.net
License: GPL
Platform: UNKNOWN
Classifier: Framework :: Plone
Classifier: Framework :: Zope2
Classifier: Framework :: Zope3
Classifier: Programming Language :: Python
Classifier: Topic :: Software Development :: Libraries :: Python Modules
